nudenetupdated/__init__.py
nudenetupdated/classifier.py
nudenetupdated/detector.py
nudenetupdated/utils/__init__.py
nudenetupdated/utils/detector.py
nudenetupdated/utils/download.py
nudenetupdated/utils/image.py
nudenetupdated-2.2.10.dist-info/LICENSE.md
nudenetupdated-2.2.10.dist-info/METADATA
nudenetupdated-2.2.10.dist-info/WHEEL
nudenetupdated-2.2.10.dist-info/RECORD
