Metadata-Version: 2.1
Name: NudeNetUpdated
Version: 2.2.10
Summary: 
Author: ELoiselle
Author-email: emile.loiselle@hotmail.com
Requires-Python: >=3.10,<4.0
Classifier: Programming Language :: Python :: 3
Classifier: Programming Language :: Python :: 3.10
Classifier: Programming Language :: Python :: 3.11
Requires-Dist: numpy (>=1.25.2,<2.0.0)
Requires-Dist: onnxruntime (>=1.15.1,<2.0.0)
Requires-Dist: opencv-python-headless (>=4.5.1.48)
Requires-Dist: pillow (>=10.0.0,<11.0.0)
Requires-Dist: progressbar (>=2.5,<3.0)
Requires-Dist: pydload (>=1.0.9,<2.0.0)
Requires-Dist: scikit-image (>=0.21.0,<0.22.0)
